[
  {
    "start": 4.02,
    "end": 5.34,
    "name": "Daniel",
    "duration": 1.3200000000000003
  },
  {
    "start": 15.99,
    "end": 17.79,
    "name": "Daniel",
    "duration": 1.799999999999999
  },
  {
    "start": 265.14,
    "end": 266.22,
    "name": "Lia",
    "duration": 1.080000000000041
  },
  {
    "start": 279.36,
    "end": 281.49,
    "name": "Lia",
    "duration": 2.1299999999999955
  },
  {
    "start": 306.72,
    "end": 308.31,
    "name": "Daniel",
    "duration": 1.589999999999975
  },
  {
    "start": 2855.4,
    "end": 2858.304,
    "name": "Daniel",
    "duration": 2.9039999999999964
  }
]